{"id": 160640, "ano": 2026, "mes_atual": "02", "gasto_ano": 14301.2, "gasto_mes": 0.0, "por_mes": {}, "por_categoria": {"MANUTENÇÃO DE ESCRITÓRIO DE APOIO À ATIVIDADE PARLAMENTAR": 1575.0, "COMBUSTÍVEIS E LUBRIFICANTES.": 2862.9, "DIVULGAÇÃO DA ATIVIDADE PARLAMENTAR.": 1800.0, "HOSPEDAGEM ,EXCETO DO PARLAMENTAR NO DISTRITO FEDERAL.": 2173.3, "LOCAÇÃO OU FRETAMENTO DE VEÍCULOS AUTOMOTORES": 5890.0}, "por_fornecedor": {"PARLANET WEB E TECNOLOGIA EIRELI": 1575.0, "AUTO POSTO REDECK LTDA": 100.0, "COMERCIAL MINAS GRILL LTDA": 258.61, "JR COMERCIO E PRESTACAO DE SERVICOS LTDA": 2055.81, "POSTO DE COMBUSTIVEIS EPIA CANDANGOLANDIA LTDA": 204.64, "POSTO DE SERVIÇOS R R 33 LTDA": 243.84, "GILBERTO SILVEIRA JUNIOR": 1800.0, "DANIELA DE CARVALHO VAZ JACOB-ME HOTEL AGUA VIVA": 1521.3, "PORTO BELLO HOSPEDAGEM E ALIMENTACAO LTDA": 652.0, "ESTRELA LOGISTICA LTDA": 5890.0}, "lancamentos": [{"data": "", "categoria": "MANUTENÇÃO DE ESCRITÓRIO DE APOIO À ATIVIDADE PARLAMENTAR", "fornecedor": "PARLANET WEB E TECNOLOGIA EIRELI", "valor": 1575.0, "documento_url": "https://www.camara.leg.br/cota-parlamentar/documentos/publ/2385/2026/8040214.pdf"}, {"data": "", "categoria": "COMBUSTÍVEIS E LUBRIFICANTES.", "fornecedor": "AUTO POSTO REDECK LTDA", "valor": 100.0, "documento_url": "https://www.camara.leg.br/cota-parlamentar/documentos/publ/2385/2026/8040218.pdf"}, {"data": "", "categoria": "COMBUSTÍVEIS E LUBRIFICANTES.", "fornecedor": "COMERCIAL MINAS GRILL LTDA", "valor": 258.61, "documento_url": "https://www.camara.leg.br/cota-parlamentar/documentos/publ/2385/2026/8040236.pdf"}, {"data": "", "categoria": "COMBUSTÍVEIS E LUBRIFICANTES.", "fornecedor": "JR COMERCIO E PRESTACAO DE SERVICOS LTDA", "valor": 1199.32, "documento_url": "https://www.camara.leg.br/cota-parlamentar/documentos/publ/2385/2026/8036563.pdf"}, {"data": "", "categoria": "COMBUSTÍVEIS E LUBRIFICANTES.", "fornecedor": "JR COMERCIO E PRESTACAO DE SERVICOS LTDA", "valor": 856.49, "documento_url": "https://www.camara.leg.br/cota-parlamentar/documentos/publ/2385/2026/8040238.pdf"}, {"data": "", "categoria": "COMBUSTÍVEIS E LUBRIFICANTES.", "fornecedor": "POSTO DE COMBUSTIVEIS EPIA CANDANGOLANDIA LTDA", "valor": 204.64, "documento_url": "https://www.camara.leg.br/cota-parlamentar/nota-fiscal-eletronica?ideDocumentoFiscal=8044200"}, {"data": "", "categoria": "COMBUSTÍVEIS E LUBRIFICANTES.", "fornecedor": "POSTO DE SERVIÇOS R R 33 LTDA", "valor": 243.84, "documento_url": "https://www.camara.leg.br/cota-parlamentar/documentos/publ/2385/2026/8040234.pdf"}, {"data": "", "categoria": "DIVULGAÇÃO DA ATIVIDADE PARLAMENTAR.", "fornecedor": "GILBERTO SILVEIRA JUNIOR", "valor": 1800.0, "documento_url": "https://www.camara.leg.br/cota-parlamentar/documentos/publ/2385/2026/8040209.pdf"}, {"data": "", "categoria": "HOSPEDAGEM ,EXCETO DO PARLAMENTAR NO DISTRITO FEDERAL.", "fornecedor": "DANIELA DE CARVALHO VAZ JACOB-ME HOTEL AGUA VIVA", "valor": 792.3, "documento_url": "https://www.camara.leg.br/cota-parlamentar/documentos/publ/2385/2026/8040249.pdf"}, {"data": "", "categoria": "HOSPEDAGEM ,EXCETO DO PARLAMENTAR NO DISTRITO FEDERAL.", "fornecedor": "DANIELA DE CARVALHO VAZ JACOB-ME HOTEL AGUA VIVA", "valor": 729.0, "documento_url": "https://www.camara.leg.br/cota-parlamentar/documentos/publ/2385/2026/8040230.pdf"}, {"data": "", "categoria": "HOSPEDAGEM ,EXCETO DO PARLAMENTAR NO DISTRITO FEDERAL.", "fornecedor": "PORTO BELLO HOSPEDAGEM E ALIMENTACAO LTDA", "valor": 326.0, "documento_url": "https://www.camara.leg.br/cota-parlamentar/documentos/publ/2385/2026/8040227.pdf"}, {"data": "", "categoria": "HOSPEDAGEM ,EXCETO DO PARLAMENTAR NO DISTRITO FEDERAL.", "fornecedor": "PORTO BELLO HOSPEDAGEM E ALIMENTACAO LTDA", "valor": 326.0, "documento_url": "https://www.camara.leg.br/cota-parlamentar/documentos/publ/2385/2026/8040225.pdf"}, {"data": "", "categoria": "LOCAÇÃO OU FRETAMENTO DE VEÍCULOS AUTOMOTORES", "fornecedor": "ESTRELA LOGISTICA LTDA", "valor": 5890.0, "documento_url": "https://www.camara.leg.br/cota-parlamentar/documentos/publ/2385/2026/8043280.pdf"}]}