{"id": 205865, "ano": 2026, "mes_atual": "02", "gasto_ano": 75929.85, "gasto_mes": 0.0, "por_mes": {}, "por_categoria": {"MANUTENÇÃO DE ESCRITÓRIO DE APOIO À ATIVIDADE PARLAMENTAR": 3442.23, "COMBUSTÍVEIS E LUBRIFICANTES.": 3679.44, "DIVULGAÇÃO DA ATIVIDADE PARLAMENTAR.": 60000.0, "TELEFONIA": 545.27, "LOCAÇÃO OU FRETAMENTO DE VEÍCULOS AUTOMOTORES": 8100.0, "SERVIÇO DE TÁXI, PEDÁGIO E ESTACIONAMENTO": 162.91}, "por_fornecedor": {"COND EDIF WORLD BUSINESS": 1036.22, "Copel Distribuição S.A.": 94.69, "FAG ADMINISTRAÇÃO E PARTICIPAÇÕES LTDA": 2011.97, "GP SISTEMAS E SERVIÇOS LTDA": 299.35, "AUTO POSTO LAGO NORTE LTDA": 242.45, "AUTO POSTO MARFIM LTDA": 415.94, "AUTO POSTO NOSSA SENHORA APARECIDA LTDA": 295.5, "AUTO POSTO R JUVEVE LTDA": 369.94, "AUTO POSTO SOCIAL LTDA.": 392.7, "CARREFOUR COM. E IND. LTDA": 275.63, "POSTO SILVA JARDIM LTDA": 312.66, "RMZ FUKAMI COMERCIO DE COMBUSTIVEIS LTDA ME": 689.36, "RUDNICK E CIA LTDA - MATRIZ": 685.26, "CENTRAL PARANAENSE DE COMUNICAÇÃO LTDA-ME": 50000.0, "OVERCOME PUBLICIDADE E MARKETING LTDA": 10000.0, "Claro NXT Telecomunicações S.A": 126.28, "Telefônica Brasil S.A. VIVO": 418.99, "BARIGUI LOCADORA DE VEÍCULOS LTDA": 8100.0, "UBER DO BRASIL TECNOLOGIA LTDA.": 162.91}, "lancamentos": [{"data": "", "categoria": "MANUTENÇÃO DE ESCRITÓRIO DE APOIO À ATIVIDADE PARLAMENTAR", "fornecedor": "COND EDIF WORLD BUSINESS", "valor": 1036.22, "documento_url": "https://www.camara.leg.br/cota-parlamentar/documentos/publ/3438/2026/8045313.pdf"}, {"data": "", "categoria": "MANUTENÇÃO DE ESCRITÓRIO DE APOIO À ATIVIDADE PARLAMENTAR", "fornecedor": "Copel Distribuição S.A.", "valor": 94.69, "documento_url": "https://www.camara.leg.br/cota-parlamentar/documentos/publ/3438/2026/8041903.pdf"}, {"data": "", "categoria": "MANUTENÇÃO DE ESCRITÓRIO DE APOIO À ATIVIDADE PARLAMENTAR", "fornecedor": "FAG ADMINISTRAÇÃO E PARTICIPAÇÕES LTDA", "valor": 2011.97, "documento_url": "https://www.camara.leg.br/cota-parlamentar/documentos/publ/3438/2026/8048165.pdf"}, {"data": "", "categoria": "MANUTENÇÃO DE ESCRITÓRIO DE APOIO À ATIVIDADE PARLAMENTAR", "fornecedor": "GP SISTEMAS E SERVIÇOS LTDA", "valor": 299.35, "documento_url": "https://www.camara.leg.br/cota-parlamentar/documentos/publ/3438/2026/8043538.pdf"}, {"data": "", "categoria": "COMBUSTÍVEIS E LUBRIFICANTES.", "fornecedor": "AUTO POSTO LAGO NORTE LTDA", "valor": 242.45, "documento_url": "https://www.camara.leg.br/cota-parlamentar/nota-fiscal-eletronica?ideDocumentoFiscal=8043983"}, {"data": "", "categoria": "COMBUSTÍVEIS E LUBRIFICANTES.", "fornecedor": "AUTO POSTO MARFIM LTDA", "valor": 415.94, "documento_url": "https://www.camara.leg.br/cota-parlamentar/nota-fiscal-eletronica?ideDocumentoFiscal=8046816"}, {"data": "", "categoria": "COMBUSTÍVEIS E LUBRIFICANTES.", "fornecedor": "AUTO POSTO NOSSA SENHORA APARECIDA LTDA", "valor": 295.5, "documento_url": "https://www.camara.leg.br/cota-parlamentar/nota-fiscal-eletronica?ideDocumentoFiscal=8052121"}, {"data": "", "categoria": "COMBUSTÍVEIS E LUBRIFICANTES.", "fornecedor": "AUTO POSTO R JUVEVE LTDA", "valor": 369.94, "documento_url": "https://www.camara.leg.br/cota-parlamentar/nota-fiscal-eletronica?ideDocumentoFiscal=8050538"}, {"data": "", "categoria": "COMBUSTÍVEIS E LUBRIFICANTES.", "fornecedor": "AUTO POSTO SOCIAL LTDA.", "valor": 392.7, "documento_url": "https://www.camara.leg.br/cota-parlamentar/nota-fiscal-eletronica?ideDocumentoFiscal=8039047"}, {"data": "", "categoria": "COMBUSTÍVEIS E LUBRIFICANTES.", "fornecedor": "CARREFOUR COM. E IND. LTDA", "valor": 275.63, "documento_url": "https://www.camara.leg.br/cota-parlamentar/nota-fiscal-eletronica?ideDocumentoFiscal=8052123"}, {"data": "", "categoria": "COMBUSTÍVEIS E LUBRIFICANTES.", "fornecedor": "POSTO SILVA JARDIM LTDA", "valor": 312.66, "documento_url": "https://www.camara.leg.br/cota-parlamentar/nota-fiscal-eletronica?ideDocumentoFiscal=8052122"}, {"data": "", "categoria": "COMBUSTÍVEIS E LUBRIFICANTES.", "fornecedor": "RMZ FUKAMI COMERCIO DE COMBUSTIVEIS LTDA ME", "valor": 389.36, "documento_url": "https://www.camara.leg.br/cota-parlamentar/nota-fiscal-eletronica?ideDocumentoFiscal=8041012"}, {"data": "", "categoria": "COMBUSTÍVEIS E LUBRIFICANTES.", "fornecedor": "RMZ FUKAMI COMERCIO DE COMBUSTIVEIS LTDA ME", "valor": 300.0, "documento_url": "https://www.camara.leg.br/cota-parlamentar/nota-fiscal-eletronica?ideDocumentoFiscal=8048164"}, {"data": "", "categoria": "COMBUSTÍVEIS E LUBRIFICANTES.", "fornecedor": "RUDNICK E CIA LTDA - MATRIZ", "valor": 358.1, "documento_url": "https://www.camara.leg.br/cota-parlamentar/nota-fiscal-eletronica?ideDocumentoFiscal=8036559"}, {"data": "", "categoria": "COMBUSTÍVEIS E LUBRIFICANTES.", "fornecedor": "RUDNICK E CIA LTDA - MATRIZ", "valor": 327.16, "documento_url": "https://www.camara.leg.br/cota-parlamentar/nota-fiscal-eletronica?ideDocumentoFiscal=8039044"}, {"data": "", "categoria": "DIVULGAÇÃO DA ATIVIDADE PARLAMENTAR.", "fornecedor": "CENTRAL PARANAENSE DE COMUNICAÇÃO LTDA-ME", "valor": 25000.0, "documento_url": "https://www.camara.leg.br/cota-parlamentar/documentos/publ/3438/2026/8038036.pdf"}, {"data": "", "categoria": "DIVULGAÇÃO DA ATIVIDADE PARLAMENTAR.", "fornecedor": "CENTRAL PARANAENSE DE COMUNICAÇÃO LTDA-ME", "valor": 25000.0, "documento_url": "https://www.camara.leg.br/cota-parlamentar/documentos/publ/3438/2026/8050537.pdf"}, {"data": "", "categoria": "DIVULGAÇÃO DA ATIVIDADE PARLAMENTAR.", "fornecedor": "OVERCOME PUBLICIDADE E MARKETING LTDA", "valor": 5000.0, "documento_url": "https://www.camara.leg.br/cota-parlamentar/documentos/publ/3438/2026/8036651.pdf"}, {"data": "", "categoria": "DIVULGAÇÃO DA ATIVIDADE PARLAMENTAR.", "fornecedor": "OVERCOME PUBLICIDADE E MARKETING LTDA", "valor": 5000.0, "documento_url": "https://www.camara.leg.br/cota-parlamentar/documentos/publ/3438/2026/8044986.pdf"}, {"data": "", "categoria": "TELEFONIA", "fornecedor": "Claro NXT Telecomunicações S.A", "valor": 126.28, "documento_url": ""}, {"data": "", "categoria": "TELEFONIA", "fornecedor": "Telefônica Brasil S.A. VIVO", "valor": 418.99, "documento_url": ""}, {"data": "", "categoria": "LOCAÇÃO OU FRETAMENTO DE VEÍCULOS AUTOMOTORES", "fornecedor": "BARIGUI LOCADORA DE VEÍCULOS LTDA", "valor": 8100.0, "documento_url": "https://www.camara.leg.br/cota-parlamentar/documentos/publ/3438/2026/8039566.pdf"}, {"data": "", "categoria": "SERVIÇO DE TÁXI, PEDÁGIO E ESTACIONAMENTO", "fornecedor": "UBER DO BRASIL TECNOLOGIA LTDA.", "valor": 24.99, "documento_url": "https://www.camara.leg.br/cota-parlamentar/documentos/publ/3438/2026/8046401.pdf"}, {"data": "", "categoria": "SERVIÇO DE TÁXI, PEDÁGIO E ESTACIONAMENTO", "fornecedor": "UBER DO BRASIL TECNOLOGIA LTDA.", "valor": 26.99, "documento_url": "https://www.camara.leg.br/cota-parlamentar/documentos/publ/3438/2026/8046396.pdf"}, {"data": "", "categoria": "SERVIÇO DE TÁXI, PEDÁGIO E ESTACIONAMENTO", "fornecedor": "UBER DO BRASIL TECNOLOGIA LTDA.", "valor": 62.98, "documento_url": "https://www.camara.leg.br/cota-parlamentar/documentos/publ/3438/2026/8046392.pdf"}, {"data": "", "categoria": "SERVIÇO DE TÁXI, PEDÁGIO E ESTACIONAMENTO", "fornecedor": "UBER DO BRASIL TECNOLOGIA LTDA.", "valor": 23.97, "documento_url": "https://www.camara.leg.br/cota-parlamentar/documentos/publ/3438/2026/8046394.pdf"}, {"data": "", "categoria": "SERVIÇO DE TÁXI, PEDÁGIO E ESTACIONAMENTO", "fornecedor": "UBER DO BRASIL TECNOLOGIA LTDA.", "valor": 23.98, "documento_url": "https://www.camara.leg.br/cota-parlamentar/documentos/publ/3438/2026/8046403.pdf"}]}