{"id": 220572, "ano": 2026, "mes_atual": "02", "gasto_ano": 23688.18, "gasto_mes": 0.0, "por_mes": {}, "por_categoria": {"MANUTENÇÃO DE ESCRITÓRIO DE APOIO À ATIVIDADE PARLAMENTAR": 377.78, "COMBUSTÍVEIS E LUBRIFICANTES.": 3640.16, "DIVULGAÇÃO DA ATIVIDADE PARLAMENTAR.": 15000.0, "TELEFONIA": 170.24, "LOCAÇÃO OU FRETAMENTO DE VEÍCULOS AUTOMOTORES": 4500.0}, "por_fornecedor": {"EQUATORIAL GOIáS DISTRIBUIDORA DE ENERGIA S.A": 305.67, "SANEAGO": 72.11, "031 - 302 NORTE - CASCOL COMBUSTIVEIS PARA VEICULOS LTDA": 355.63, "072 - 403 SUL - CASCOL COMBUSTIVEIS PARA VEICULOS LTDA": 105.15, "AUTO POSTO CHIMARRAO LTDA": 100.0, "COMERCIAL DE DERIVADO DE PETROLEO SAO CARLOS LTDA": 157.39, "COOPERATIVA AGROPECUARIA MISTA DE PIRACANJUBA - COAPIL": 424.51, "DECIO L13 LIMITADA": 100.0, "PAULO ROBERTO DE OLIVEIRA ROHDEN LTDA": 440.27, "POSTO SERRA DOURADA LTDA": 301.9, "POSTO Z+Z SANTA MARTA LTDA": 359.09, "Rrs Auto Posto Ltda": 1296.22, "MX LOAD LTDA ME": 15000.0, "Claro NXT Telecomunicações S.A": 170.24, "RS PRODUTOS E SERVICOS EIRELI": 4500.0}, "lancamentos": [{"data": "", "categoria": "MANUTENÇÃO DE ESCRITÓRIO DE APOIO À ATIVIDADE PARLAMENTAR", "fornecedor": "EQUATORIAL GOIáS DISTRIBUIDORA DE ENERGIA S.A", "valor": 305.67, "documento_url": "https://www.camara.leg.br/cota-parlamentar/documentos/publ/3638/2026/8043372.pdf"}, {"data": "", "categoria": "MANUTENÇÃO DE ESCRITÓRIO DE APOIO À ATIVIDADE PARLAMENTAR", "fornecedor": "SANEAGO", "valor": 72.11, "documento_url": "https://www.camara.leg.br/cota-parlamentar/documentos/publ/3638/2026/8043361.pdf"}, {"data": "", "categoria": "COMBUSTÍVEIS E LUBRIFICANTES.", "fornecedor": "031 - 302 NORTE - CASCOL COMBUSTIVEIS PARA VEICULOS LTDA", "valor": 355.63, "documento_url": "https://www.camara.leg.br/cota-parlamentar/nota-fiscal-eletronica?ideDocumentoFiscal=8041893"}, {"data": "", "categoria": "COMBUSTÍVEIS E LUBRIFICANTES.", "fornecedor": "072 - 403 SUL - CASCOL COMBUSTIVEIS PARA VEICULOS LTDA", "valor": 105.15, "documento_url": "https://www.camara.leg.br/cota-parlamentar/nota-fiscal-eletronica?ideDocumentoFiscal=8049535"}, {"data": "", "categoria": "COMBUSTÍVEIS E LUBRIFICANTES.", "fornecedor": "AUTO POSTO CHIMARRAO LTDA", "valor": 100.0, "documento_url": "https://www.camara.leg.br/cota-parlamentar/nota-fiscal-eletronica?ideDocumentoFiscal=8041900"}, {"data": "", "categoria": "COMBUSTÍVEIS E LUBRIFICANTES.", "fornecedor": "COMERCIAL DE DERIVADO DE PETROLEO SAO CARLOS LTDA", "valor": 157.39, "documento_url": "https://www.camara.leg.br/cota-parlamentar/nota-fiscal-eletronica?ideDocumentoFiscal=8049530"}, {"data": "", "categoria": "COMBUSTÍVEIS E LUBRIFICANTES.", "fornecedor": "COOPERATIVA AGROPECUARIA MISTA DE PIRACANJUBA - COAPIL", "valor": 424.51, "documento_url": "https://www.camara.leg.br/cota-parlamentar/nota-fiscal-eletronica?ideDocumentoFiscal=8046099"}, {"data": "", "categoria": "COMBUSTÍVEIS E LUBRIFICANTES.", "fornecedor": "DECIO L13 LIMITADA", "valor": 100.0, "documento_url": "https://www.camara.leg.br/cota-parlamentar/nota-fiscal-eletronica?ideDocumentoFiscal=8041884"}, {"data": "", "categoria": "COMBUSTÍVEIS E LUBRIFICANTES.", "fornecedor": "PAULO ROBERTO DE OLIVEIRA ROHDEN LTDA", "valor": 440.27, "documento_url": "https://www.camara.leg.br/cota-parlamentar/nota-fiscal-eletronica?ideDocumentoFiscal=8046118"}, {"data": "", "categoria": "COMBUSTÍVEIS E LUBRIFICANTES.", "fornecedor": "POSTO SERRA DOURADA LTDA", "valor": 301.9, "documento_url": "https://www.camara.leg.br/cota-parlamentar/nota-fiscal-eletronica?ideDocumentoFiscal=8046166"}, {"data": "", "categoria": "COMBUSTÍVEIS E LUBRIFICANTES.", "fornecedor": "POSTO Z+Z SANTA MARTA LTDA", "valor": 359.09, "documento_url": "https://www.camara.leg.br/cota-parlamentar/nota-fiscal-eletronica?ideDocumentoFiscal=8041905"}, {"data": "", "categoria": "COMBUSTÍVEIS E LUBRIFICANTES.", "fornecedor": "Rrs Auto Posto Ltda", "valor": 255.11, "documento_url": "https://www.camara.leg.br/cota-parlamentar/nota-fiscal-eletronica?ideDocumentoFiscal=8041880"}, {"data": "", "categoria": "COMBUSTÍVEIS E LUBRIFICANTES.", "fornecedor": "Rrs Auto Posto Ltda", "valor": 160.89, "documento_url": "https://www.camara.leg.br/cota-parlamentar/nota-fiscal-eletronica?ideDocumentoFiscal=8046178"}, {"data": "", "categoria": "COMBUSTÍVEIS E LUBRIFICANTES.", "fornecedor": "Rrs Auto Posto Ltda", "valor": 179.34, "documento_url": "https://www.camara.leg.br/cota-parlamentar/nota-fiscal-eletronica?ideDocumentoFiscal=8046086"}, {"data": "", "categoria": "COMBUSTÍVEIS E LUBRIFICANTES.", "fornecedor": "Rrs Auto Posto Ltda", "valor": 334.54, "documento_url": "https://www.camara.leg.br/cota-parlamentar/nota-fiscal-eletronica?ideDocumentoFiscal=8039939"}, {"data": "", "categoria": "COMBUSTÍVEIS E LUBRIFICANTES.", "fornecedor": "Rrs Auto Posto Ltda", "valor": 366.34, "documento_url": "https://www.camara.leg.br/cota-parlamentar/nota-fiscal-eletronica?ideDocumentoFiscal=8037906"}, {"data": "", "categoria": "DIVULGAÇÃO DA ATIVIDADE PARLAMENTAR.", "fornecedor": "MX LOAD LTDA ME", "valor": 15000.0, "documento_url": "https://www.camara.leg.br/cota-parlamentar/documentos/publ/3638/2026/8045922.pdf"}, {"data": "", "categoria": "TELEFONIA", "fornecedor": "Claro NXT Telecomunicações S.A", "valor": 170.24, "documento_url": ""}, {"data": "", "categoria": "LOCAÇÃO OU FRETAMENTO DE VEÍCULOS AUTOMOTORES", "fornecedor": "RS PRODUTOS E SERVICOS EIRELI", "valor": 4500.0, "documento_url": "https://www.camara.leg.br/cota-parlamentar/documentos/publ/3638/2026/8049217.pdf"}]}