{"id": 74075, "ano": 2026, "mes_atual": "03", "gasto_ano": 5977.47, "gasto_mes": 0.0, "por_mes": {}, "por_categoria": {"MANUTENÇÃO DE ESCRITÓRIO DE APOIO À ATIVIDADE PARLAMENTAR": 1160.0, "COMBUSTÍVEIS E LUBRIFICANTES.": 4007.47, "TELEFONIA": 432.6, "FORNECIMENTO DE ALIMENTAÇÃO DO PARLAMENTAR": 377.4}, "por_fornecedor": {"Conde & Dell Aringa - Des de Softwares": 1160.0, "063 - 311 SUL - CASCOL COMBUSTIVEIS PARA VEICULOS LTDA": 200.0, "CHERMONT RODRIGUES E CIA LTDA": 250.0, "POSTO ALIANCA LTDA": 300.0, "POSTO ICCAR LTDA": 250.0, "POSTO MAGUARI LTDA": 300.0, "Abejet Comercio de Combustivel e Lubrificantes Ltda": 2707.47, "Claro NXT Telecomunicações S.A": 432.6, "DUVAN BAR E RESTAURANTE LTDA": 142.0, "M. P. VASCONCELOS": 70.5, "POBRE JUAN RESTAURANTE GRILL LTDA": 124.0, "SERVICO NACIONAL DE APREND. COMERCIAL": 40.9}, "lancamentos": [{"data": "", "categoria": "MANUTENÇÃO DE ESCRITÓRIO DE APOIO À ATIVIDADE PARLAMENTAR", "fornecedor": "Conde & Dell Aringa - Des de Softwares", "valor": 580.0, "documento_url": "https://www.camara.leg.br/cota-parlamentar/documentos/publ/1011/2026/8044154.pdf"}, {"data": "", "categoria": "MANUTENÇÃO DE ESCRITÓRIO DE APOIO À ATIVIDADE PARLAMENTAR", "fornecedor": "Conde & Dell Aringa - Des de Softwares", "valor": 580.0, "documento_url": "https://www.camara.leg.br/cota-parlamentar/documentos/publ/1011/2026/8057996.pdf"}, {"data": "", "categoria": "COMBUSTÍVEIS E LUBRIFICANTES.", "fornecedor": "063 - 311 SUL - CASCOL COMBUSTIVEIS PARA VEICULOS LTDA", "valor": 200.0, "documento_url": "https://www.camara.leg.br/cota-parlamentar/nota-fiscal-eletronica?ideDocumentoFiscal=8050886"}, {"data": "", "categoria": "COMBUSTÍVEIS E LUBRIFICANTES.", "fornecedor": "CHERMONT RODRIGUES E CIA LTDA", "valor": 250.0, "documento_url": "https://www.camara.leg.br/cota-parlamentar/nota-fiscal-eletronica?ideDocumentoFiscal=8050859"}, {"data": "", "categoria": "COMBUSTÍVEIS E LUBRIFICANTES.", "fornecedor": "POSTO ALIANCA LTDA", "valor": 300.0, "documento_url": "https://www.camara.leg.br/cota-parlamentar/nota-fiscal-eletronica?ideDocumentoFiscal=8050875"}, {"data": "", "categoria": "COMBUSTÍVEIS E LUBRIFICANTES.", "fornecedor": "POSTO ICCAR LTDA", "valor": 250.0, "documento_url": "https://www.camara.leg.br/cota-parlamentar/nota-fiscal-eletronica?ideDocumentoFiscal=8050882"}, {"data": "", "categoria": "COMBUSTÍVEIS E LUBRIFICANTES.", "fornecedor": "POSTO MAGUARI LTDA", "valor": 300.0, "documento_url": "https://www.camara.leg.br/cota-parlamentar/nota-fiscal-eletronica?ideDocumentoFiscal=8050884"}, {"data": "", "categoria": "COMBUSTÍVEIS E LUBRIFICANTES.", "fornecedor": "Abejet Comercio de Combustivel e Lubrificantes Ltda", "valor": 2707.47, "documento_url": "https://www.camara.leg.br/cota-parlamentar/nota-fiscal-eletronica?ideDocumentoFiscal=8061551"}, {"data": "", "categoria": "TELEFONIA", "fornecedor": "Claro NXT Telecomunicações S.A", "valor": 216.3, "documento_url": ""}, {"data": "", "categoria": "TELEFONIA", "fornecedor": "Claro NXT Telecomunicações S.A", "valor": 216.3, "documento_url": ""}, {"data": "", "categoria": "FORNECIMENTO DE ALIMENTAÇÃO DO PARLAMENTAR", "fornecedor": "DUVAN BAR E RESTAURANTE LTDA", "valor": 142.0, "documento_url": "https://www.camara.leg.br/cota-parlamentar/nota-fiscal-eletronica?ideDocumentoFiscal=8046847"}, {"data": "", "categoria": "FORNECIMENTO DE ALIMENTAÇÃO DO PARLAMENTAR", "fornecedor": "M. P. VASCONCELOS", "valor": 34.0, "documento_url": "https://www.camara.leg.br/cota-parlamentar/nota-fiscal-eletronica?ideDocumentoFiscal=8050867"}, {"data": "", "categoria": "FORNECIMENTO DE ALIMENTAÇÃO DO PARLAMENTAR", "fornecedor": "M. P. VASCONCELOS", "valor": 36.5, "documento_url": "https://www.camara.leg.br/cota-parlamentar/nota-fiscal-eletronica?ideDocumentoFiscal=8050869"}, {"data": "", "categoria": "FORNECIMENTO DE ALIMENTAÇÃO DO PARLAMENTAR", "fornecedor": "POBRE JUAN RESTAURANTE GRILL LTDA", "valor": 124.0, "documento_url": "https://www.camara.leg.br/cota-parlamentar/nota-fiscal-eletronica?ideDocumentoFiscal=8059907"}, {"data": "", "categoria": "FORNECIMENTO DE ALIMENTAÇÃO DO PARLAMENTAR", "fornecedor": "SERVICO NACIONAL DE APREND. COMERCIAL", "valor": 24.92, "documento_url": "https://www.camara.leg.br/cota-parlamentar/nota-fiscal-eletronica?ideDocumentoFiscal=8050889"}, {"data": "", "categoria": "FORNECIMENTO DE ALIMENTAÇÃO DO PARLAMENTAR", "fornecedor": "SERVICO NACIONAL DE APREND. COMERCIAL", "valor": 15.98, "documento_url": "https://www.camara.leg.br/cota-parlamentar/nota-fiscal-eletronica?ideDocumentoFiscal=8059896"}]}