{"id": 74084, "ano": 2026, "mes_atual": "02", "gasto_ano": 16497.55, "gasto_mes": 0.0, "por_mes": {}, "por_categoria": {"MANUTENÇÃO DE ESCRITÓRIO DE APOIO À ATIVIDADE PARLAMENTAR": 10089.87, "COMBUSTÍVEIS E LUBRIFICANTES.": 207.68, "DIVULGAÇÃO DA ATIVIDADE PARLAMENTAR.": 6200.0}, "por_fornecedor": {"AMORETTO CAFES EXPRESSO LTDA": 960.0, "Condominio Edifício Cristal Corporate - GARAGEM 00053S": 1362.29, "EQUATORIAL PARÁ DISTRIBUIDORA DE ENERGIA S.A.": 292.58, "MARIA JOELMA MOTA SOUSA": 7475.0, "AUTO POSTO 305 SUL LTDA.": 207.68, "DANIEL CARLOS PINTOS LOPES": 1600.0, "JOÃO PAULO RODRIGUES PEIXOTO": 1600.0, "MARIA PAULA PINHEIRO MANSUR 01344782230": 3000.0}, "lancamentos": [{"data": "", "categoria": "MANUTENÇÃO DE ESCRITÓRIO DE APOIO À ATIVIDADE PARLAMENTAR", "fornecedor": "AMORETTO CAFES EXPRESSO LTDA", "valor": 960.0, "documento_url": "https://www.camara.leg.br/cota-parlamentar/documentos/publ/1150/2026/8047311.pdf"}, {"data": "", "categoria": "MANUTENÇÃO DE ESCRITÓRIO DE APOIO À ATIVIDADE PARLAMENTAR", "fornecedor": "Condominio Edifício Cristal Corporate - GARAGEM 00053S", "valor": 1362.29, "documento_url": "https://www.camara.leg.br/cota-parlamentar/documentos/publ/1150/2026/8048330.pdf"}, {"data": "", "categoria": "MANUTENÇÃO DE ESCRITÓRIO DE APOIO À ATIVIDADE PARLAMENTAR", "fornecedor": "EQUATORIAL PARÁ DISTRIBUIDORA DE ENERGIA S.A.", "valor": 195.0, "documento_url": "https://www.camara.leg.br/cota-parlamentar/documentos/publ/1150/2026/8044628.pdf"}, {"data": "", "categoria": "MANUTENÇÃO DE ESCRITÓRIO DE APOIO À ATIVIDADE PARLAMENTAR", "fornecedor": "EQUATORIAL PARÁ DISTRIBUIDORA DE ENERGIA S.A.", "valor": 97.58, "documento_url": "https://www.camara.leg.br/cota-parlamentar/documentos/publ/1150/2026/8044603.pdf"}, {"data": "", "categoria": "MANUTENÇÃO DE ESCRITÓRIO DE APOIO À ATIVIDADE PARLAMENTAR", "fornecedor": "MARIA JOELMA MOTA SOUSA", "valor": 7475.0, "documento_url": "https://www.camara.leg.br/cota-parlamentar/documentos/publ/1150/2026/8044573.pdf"}, {"data": "", "categoria": "COMBUSTÍVEIS E LUBRIFICANTES.", "fornecedor": "AUTO POSTO 305 SUL LTDA.", "valor": 207.68, "documento_url": "https://www.camara.leg.br/cota-parlamentar/nota-fiscal-eletronica?ideDocumentoFiscal=8046632"}, {"data": "", "categoria": "DIVULGAÇÃO DA ATIVIDADE PARLAMENTAR.", "fornecedor": "DANIEL CARLOS PINTOS LOPES", "valor": 1600.0, "documento_url": "https://www.camara.leg.br/cota-parlamentar/documentos/publ/1150/2026/8044535.pdf"}, {"data": "", "categoria": "DIVULGAÇÃO DA ATIVIDADE PARLAMENTAR.", "fornecedor": "JOÃO PAULO RODRIGUES PEIXOTO", "valor": 1600.0, "documento_url": "https://www.camara.leg.br/cota-parlamentar/documentos/publ/1150/2026/8044561.pdf"}, {"data": "", "categoria": "DIVULGAÇÃO DA ATIVIDADE PARLAMENTAR.", "fornecedor": "MARIA PAULA PINHEIRO MANSUR 01344782230", "valor": 3000.0, "documento_url": "https://www.camara.leg.br/cota-parlamentar/documentos/publ/1150/2026/8044512.pdf"}]}